CHANGES.txt
bootstrap.py
buildout.cfg
setup.py
src/z3c/__init__.py
src/z3c.resourcecollector.egg-info/PKG-INFO
src/z3c.resourcecollector.egg-info/SOURCES.txt
src/z3c.resourcecollector.egg-info/dependency_links.txt
src/z3c.resourcecollector.egg-info/namespace_packages.txt
src/z3c.resourcecollector.egg-info/not-zip-safe
src/z3c.resourcecollector.egg-info/requires.txt
src/z3c.resourcecollector.egg-info/top_level.txt
src/z3c/resourcecollector/__init__.py
src/z3c/resourcecollector/browser.py
src/z3c/resourcecollector/interfaces.py
src/z3c/resourcecollector/meta.zcml
src/z3c/resourcecollector/tests.py
src/z3c/resourcecollector/testview.py
src/z3c/resourcecollector/utility.py
src/z3c/resourcecollector/z3c.resourcecollector-meta.zcml
src/z3c/resourcecollector/zcml.py
src/z3c/resourcecollector/zcml.txt
