Metadata-Version: 1.0
Name: z3c.resourcecollector
Version: 1.1.3
Summary: collects multiple resources and combines them to one
Home-page: http://launchpad.net/z3c.resourcecollector
Author: Zoltan Szabo
Author-email: zoltan.szabo@informmedia.ro
License: ZPL
Platform: UNKNOWN
